saltpylint/__init__.py
saltpylint/blacklist.py
saltpylint/dunder_del.py
saltpylint/fileperms.py
saltpylint/smartup.py
saltpylint/thirdparty.py
saltpylint/version.py
saltpylint/virt.py
SaltPyLint-2024.2.5.dist-info/LICENSE
SaltPyLint-2024.2.5.dist-info/METADATA
SaltPyLint-2024.2.5.dist-info/WHEEL
SaltPyLint-2024.2.5.dist-info/top_level.txt
SaltPyLint-2024.2.5.dist-info/RECORD
