Metadata-Version: 2.1
Name: SaltPyLint
Version: 2024.2.5
Summary: Required PyLint plugins needed in the several SaltStack projects.
Home-page: https://github.com/saltstack/salt-pylint
Author: Pedro Algarvio
Author-email: pedro@algarvio.me
License: Apache Software License 2.0
Project-URL: Source, https://github.com/saltstack/salt-pylint
Project-URL: Tracker, https://github.com/saltstack/salt-pylint/issues
Project-URL: Documentation, https://salt-pylint.readthedocs.io
Platform: unix
Platform: linux
Platform: osx
Platform: cygwin
Platform: win32
Classifier: Programming Language :: Python
Classifier: Programming Language :: Cython
Classifier: Programming Language :: Python :: 3
Classifier: Programming Language :: Python :: 3 :: Only
Classifier: Programming Language :: Python :: 3.7
Classifier: Programming Language :: Python :: 3.8
Classifier: Programming Language :: Python :: 3.9
Classifier: Programming Language :: Python :: 3.10
Classifier: Programming Language :: Python :: 3.11
Classifier: Development Status :: 5 - Production/Stable
Classifier: License :: OSI Approved :: Apache Software License
Classifier: Environment :: Console
Classifier: Intended Audience :: Developers
Classifier: Intended Audience :: Information Technology
Classifier: Intended Audience :: System Administrators
Requires-Python: >=3.8
License-File: LICENSE
Requires-Dist: PyLint
